{
  "timestamp": "2026-04-24T07:52:13.987Z",
  "question": "Resolve active source and fee-payer funding odinZ recipient found from RXRP priority counterparty follow-up.",
  "executed": true,
  "plan": {
    "walletCount": 1,
    "checks": [
      "helius-balance",
      "helius-signatures"
    ],
    "estimated": {
      "heliusCredits": 11,
      "arkhamLabelLookups": 0,
      "arkhamRowCredits": 0
    },
    "notes": [
      "Helius signature estimates use the project 10-credit class for getSignaturesForAddress.",
      "Arkham transfer row estimate is limit * 2 credits per wallet; guardrails may block tighter.",
      "Dry-run prints only the plan. Use --execute for live calls."
    ]
  },
  "wallets": [
    {
      "address": "odinFqDRznBzUHSGdZzkY78AgaCxFRoHe7GTvrvo4Dn",
      "errors": [],
      "helius_balance": {
        "lamports": 10868748569,
        "sol": 10.868748569
      },
      "helius_signatures": [
        {
          "signature": "4eQa9u5oGtX3ABLD1qmctJGtoh2jDQUyv7JMPq1TotGURo5c1oDRoCU344JDiq74CToJy67eVL1ctyiLPe4yMPPx",
          "slot": 415304207,
          "err": null,
          "memo": null,
          "blockTime": 1777017120,
          "confirmationStatus": "finalized"
        },
        {
          "signature": "3X4KKYdKiNWbNUrPoFVgHysBL1o87bf3NKVFKv7daA5T9pjzbMHqNqP24Pctv8eKAd3MYYfb6Foy8VghoULQZymX",
          "slot": 415304203,
          "err": {
            "InsufficientFundsForRent": {
              "account_index": 2
            }
          },
          "memo": null,
          "blockTime": 1777017118,
          "confirmationStatus": "finalized"
        },
        {
          "signature": "4UuV1YVNbL7JxtuTxUZsj1WrASKFLmgnNJnvGYMCUFBJiU2kTcVA4uJNawJ6Z5TtP3tUvEdnLiscudXpRMcxA86v",
          "slot": 415304197,
          "err": {
            "InsufficientFundsForRent": {
              "account_index": 1
            }
          },
          "memo": null,
          "blockTime": 1777017116,
          "confirmationStatus": "finalized"
        },
        {
          "signature": "2C5JPJraDpykAEK1cgYwYBmjLRY98R5thauujDN5Bw9nSA1yHn8AbfvHPEeKG56P58eStnjgB6iW5p52eQzuGcf",
          "slot": 415304196,
          "err": null,
          "memo": null,
          "blockTime": 1777017115,
          "confirmationStatus": "finalized"
        },
        {
          "signature": "3Efm7sDu3CT8Wm1VxUctLhimPeEkjrxnE8bkv5XdHhcSGgYbnwY7x6KxZ97irwdBDem1gTuNCPPemGYAthsyJ1Ei",
          "slot": 415304186,
          "err": null,
          "memo": null,
          "blockTime": 1777017111,
          "confirmationStatus": "finalized"
        }
      ]
    }
  ]
}
